urllib_ext/__init__.py
urllib_ext/parse.py
urllib_ext-2021.10.26.dist-info/LICENSE
urllib_ext-2021.10.26.dist-info/METADATA
urllib_ext-2021.10.26.dist-info/WHEEL
urllib_ext-2021.10.26.dist-info/top_level.txt
urllib_ext-2021.10.26.dist-info/RECORD
